sysprompt/__init__.py
sysprompt/cache.py
sysprompt/main.py
sysprompt/wrappers/__init__.py
sysprompt/wrappers/anthropic.py
sysprompt/wrappers/gemini.py
sysprompt/wrappers/openai.py
tests/__init__.py
sysprompt-0.1.3.dist-info/LICENSE
sysprompt-0.1.3.dist-info/METADATA
sysprompt-0.1.3.dist-info/WHEEL
sysprompt-0.1.3.dist-info/top_level.txt
sysprompt-0.1.3.dist-info/RECORD
